ripplecounter/ripplecounter.v
module ripplecounter(Q0,Q1,Q2,Q3,CP, Rd); //Ripple counter
output Q0,Q1,Q2,Q3;
input CP, Rd;
D_FF FF0(Q0, ~Q0, CP, Rd);
D_FF FF1(Q1, ~Q1, Q0, Rd);
D_FF FF2(Q2, ~Q2, Q1, Rd);
D_FF FF3(Q3, ~Q3, Q2, Rd);
endmodule

module D_FF (Q,D,CP,Rd); //module D_FF with asynchronous reset
output Q;
input D,CP,Rd;
reg Q;
always @(posedge CP or negedge Rd)
if (~Rd) Q <= 1'b0;
else Q <= D;
endmodule

ripplecounter/ripplecounter_tb.vt
`timescale 1ns/100ps
`include "ripplecounter.v"

module ripplecounter_tb;
   reg CP, Rd;
   wire Q0,Q1,Q2,Q3;
   ripplecounter counter1(Q0,Q1,Q2,Q3,CP, Rd);
   initial begin
      $dumpfile("ripplecounter.vcd");
      $dumpvars(0, ripplecounter_tb);
      Rd = 1;
      CP = 0;
      #1 Rd = 0;
      #0.5 Rd = 1;
      #28
      $finish;
   end
   always begin
      #2 CP = ~CP;
   end
endmodule

ripplecounter/ripplecounter.vcd
$date
	Sun Nov 22 17:21:34 2020
$end
$version
	Icarus Verilog
$end
$timescale
	100ps
$end
$scope module ripplecounter_tb $end
$var wire 1 ! Q3 $end
$var wire 1 " Q2 $end
$var wire 1 # Q1 $end
$var wire 1 $ Q0 $end
$var reg 1 % CP $end
$var reg 1 & Rd $end
$scope module counter1 $end
$var wire 1 % CP $end
$var wire 1 & Rd $end
$var wire 1 ! Q3 $end
$var wire 1 " Q2 $end
$var wire 1 # Q1 $end
$var wire 1 $ Q0 $end
$scope module FF0 $end
$var wire 1 % CP $end
$var wire 1 ' D $end
$var wire 1 & Rd $end
$var reg 1 $ Q $end
$upscope $end
$scope module FF1 $end
$var wire 1 $ CP $end
$var wire 1 ( D $end
$var wire 1 & Rd $end
$var reg 1 # Q $end
$upscope $end
$scope module FF2 $end
$var wire 1 # CP $end
$var wire 1 ) D $end
$var wire 1 & Rd $end
$var reg 1 " Q $end
$upscope $end
$scope module FF3 $end
$var wire 1 " CP $end
$var wire 1 * D $end
$var wire 1 & Rd $end
$var reg 1 ! Q $end
$upscope $end
$upscope $end
$upscope $end
$enddefinitions $end
#0
$dumpvars
x*
x)
x(
x'
1&
0%
x$
x#
x"
x!
$end
#10
1'
1(
1)
1*
0$
0#
0"
0!
0&
#15
1&
#20
0*
1!
0)
1"
0(
1#
0'
1$
1%
#40
0%
#60
1'
0$
1%
#80
0%
#100
1(
0#
0'
1$
1%
#120
0%
#140
1'
0$
1%
#160
0%
#180
1)
0"
0(
1#
0'
1$
1%
#200
0%
#220
1'
0$
1%
#240
0%
#260
1(
0#
0'
1$
1%
#280
0%
