Up_Down/Up_Down.v
module Up_DownCounter (Q,CP,Up_Down, CR); //IEEE 1364—1995 Syntax
input CP,Up_Down, CR; //输入端口声明
output [2:0]Q; //输出端口声明
wire UP,CP1,CP2; //中间节点声明
wire S1,S2,S3, S5,S6,S7, notQ2;
JK_FF FF0(1'b1, 1'b1, CP, Q[0], S1, CR);
JK_FF FF1(1'b1, 1'b1, CP1, Q[1], S5, CR);
JK_FF FF2(1'b1, 1'b1, CP2, Q[2], notQ2, CR);
and (S2, Q[0], Up_Down);
not (Up, Up_Down);
and (S3, S1, Up);
or (CP1, S2, S3);
and (S6, Q[1], Up_Down);
and (S7, S5, Up);
or (CP2, S6, S7);
endmodule

module JK_FF (J,K,CP,Q,Qnot,CR); //参见例6.6.6
output Q,Qnot;
input J,K,CP, CR;
reg Q;
assign Qnot = ~ Q ;
always @(posedge CP, negedge CR)
if (~CR) Q <= 0;
else begin
case ({J,K}) //根据J、K的值进行选择
2'b00: Q <= Q;
2'b01: Q <= 1'b0;
2'b10: Q <= 1'b1;
2'b11: Q <= ~ Q;
endcase
end
endmodule

Up_Down/Up_Down_tb.vt
`timescale 1ns/100ps
`include "Up_Down.v"

module Up_Down_tb;
   reg CP, Up_Down, CR;
   wire Q0, Q1, Q2;
   //assign Q0 = 0; assign Q1 = 0; assign Q2 = 0;
   Up_DownCounter counter({Q2, Q1, Q0}, CP, Up_Down, CR);
   
   initial begin
      $dumpfile("Up_Down.vcd");
      $dumpvars(0, counter);
      Up_Down = 0;
      CP = 0;
      CR = 1;
      #0.5 CR = 0;
      #0.5 CR = 1;
      #40 Up_Down = 1;
      #40
      $finish;
   end
   always begin
      #2 CP = ~CP;
   end
endmodule

Up_Down/Up_Down.vcd
$date
	Sun Nov 22 18:21:59 2020
$end
$version
	Icarus Verilog
$end
$timescale
	100ps
$end
$scope module Up_Down_tb $end
$scope module counter $end
$var wire 1 ! CP $end
$var wire 1 " CP1 $end
$var wire 1 # CP2 $end
$var wire 1 $ CR $end
$var wire 1 % S2 $end
$var wire 1 & S3 $end
$var wire 1 ' S6 $end
$var wire 1 ( S7 $end
$var wire 1 ) Up $end
$var wire 1 * Up_Down $end
$var wire 1 + notQ2 $end
$var wire 1 , S5 $end
$var wire 1 - S1 $end
$var wire 3 . Q [2:0] $end
$scope module FF0 $end
$var wire 1 ! CP $end
$var wire 1 $ CR $end
$var wire 1 / J $end
$var wire 1 0 K $end
$var wire 1 - Qnot $end
$var reg 1 1 Q $end
$upscope $end
$scope module FF1 $end
$var wire 1 " CP $end
$var wire 1 $ CR $end
$var wire 1 2 J $end
$var wire 1 3 K $end
$var wire 1 , Qnot $end
$var reg 1 4 Q $end
$upscope $end
$scope module FF2 $end
$var wire 1 # CP $end
$var wire 1 $ CR $end
$var wire 1 5 J $end
$var wire 1 6 K $end
$var wire 1 + Qnot $end
$var reg 1 7 Q $end
$upscope $end
$upscope $end
$upscope $end
$enddefinitions $end
#0
$dumpvars
x7
16
15
x4
13
12
x1
10
1/
bx .
x-
x,
x+
0*
1)
x(
0'
x&
0%
1$
x#
x"
0!
$end
#5
1"
1#
1&
1(
1-
1,
1+
01
04
b0 .
07
0$
#10
1$
#20
0"
0&
0-
b1 .
11
1!
#40
0!
#60
0#
0(
0,
14
1"
1&
1-
b10 .
01
1!
#80
0!
#100
0"
0&
0-
b11 .
11
1!
#120
0!
#140
0+
17
1#
1(
1,
04
1"
1&
1-
b100 .
01
1!
#160
0!
#180
0"
0&
0-
b101 .
11
1!
#200
0!
#220
0#
0(
0,
14
1"
1&
1-
b110 .
01
1!
#240
0!
#260
0"
0&
0-
b111 .
11
1!
#280
0!
#300
1+
07
1#
1(
1,
04
1"
1&
1-
b0 .
01
1!
#320
0!
#340
0"
0&
0-
b1 .
11
1!
#360
0!
#380
0#
0(
0,
14
1"
1&
1-
b10 .
01
1!
#400
0!
#410
0+
b110 .
17
0"
0&
1#
0)
1'
1*
#420
0#
0'
1,
04
1"
1%
0-
b101 .
11
1!
#440
0!
#460
0"
0%
1-
b100 .
01
1!
#480
0!
#500
1+
07
1#
1'
0,
14
1"
1%
0-
b11 .
11
1!
#520
0!
#540
0"
0%
1-
b10 .
01
1!
#560
0!
#580
0#
0'
1,
04
1"
1%
0-
b1 .
11
1!
#600
0!
#620
0"
0%
1-
b0 .
01
1!
#640
0!
#660
0+
17
1#
1'
0,
14
1"
1%
0-
b111 .
11
1!
#680
0!
#700
0"
0%
1-
b110 .
01
1!
#720
0!
#740
0#
0'
1,
04
1"
1%
0-
b101 .
11
1!
#760
0!
#780
0"
0%
1-
b100 .
01
1!
#800
0!
