Step_motor/Step_motor.v
module Step_motor(
input M,CP,nCR, // Input Ports
output reg A,B,C // Output Ports
);
reg [2:0] current_state, next_state;
// Parameter Declarations
parameter [2:0] S0=3'b000, S1=3'b001, S2=3'b010, S3=3'b011, S4=3'b100, S5=3'b101, S6=3'b110, S7=3'b111;

always @(posedge CP, negedge nCR)
begin
	if (~nCR) current_state <= S0;
	else current_state <= next_state;
end
always @(current_state, M)
begin
	{A, B, C} = current_state;
	case (current_state)
		S0: next_state = S1;
		S1: next_state = (M == 0) ? S5 : S3;
		S2: next_state = (M == 0) ? S3 : S6;
		S3: next_state = (M == 0) ? S1 : S2;
		S4: next_state = (M == 0) ? S6 : S5;
		S5: next_state = (M == 0) ? S4 : S1;
		S6: next_state = (M == 0) ? S2 : S4;
		S7: next_state = S6;
	endcase
end
endmodule

Step_motor/Step_motor_tb.vt
`timescale 1ns/100ps
`include "Step_motor.v"

module Up_Down_tb;
   reg M, CP, nCR;
   wire A, B, C;
   Step_motor motor(M, CP, nCR, A, B, C);
   
   initial begin
      $dumpfile("Step_motor.vcd");
      $dumpvars(0, motor);
      M = 0;
      CP = 0;
      nCR = 1;
      #0.5 nCR = 0;
      #0.5 nCR = 1;
      #30 M = 1;
      #30
      $finish;
   end
   always begin
      #2 CP = ~CP;
   end
endmodule

Step_motor/Step_motor.vcd
$date
	Sun Nov 22 18:34:49 2020
$end
$version
	Icarus Verilog
$end
$timescale
	100ps
$end
$scope module Up_Down_tb $end
$scope module motor $end
$var wire 1 ! CP $end
$var wire 1 " M $end
$var wire 1 # nCR $end
$var reg 1 $ A $end
$var reg 1 % B $end
$var reg 1 & C $end
$var reg 3 ' current_state [2:0] $end
$var reg 3 ( next_state [2:0] $end
$upscope $end
$upscope $end
$enddefinitions $end
#0
$dumpvars
bx (
bx '
x&
x%
x$
1#
0"
0!
$end
#5
b1 (
0$
0%
0&
b0 '
0#
#10
1#
#20
b101 (
1&
b1 '
1!
#40
0!
#60
b100 (
1$
b101 '
1!
#80
0!
#100
b110 (
0&
b100 '
1!
#120
0!
#140
b10 (
1%
b110 '
1!
#160
0!
#180
b11 (
0$
b10 '
1!
#200
0!
#220
b1 (
1&
b11 '
1!
#240
0!
#260
b101 (
0%
b1 '
1!
#280
0!
#300
b100 (
1$
b101 '
1!
#310
b1 (
1"
#320
0!
#340
b11 (
0$
b1 '
1!
#360
0!
#380
b10 (
1%
b11 '
1!
#400
0!
#420
b110 (
0&
b10 '
1!
#440
0!
#460
b100 (
1$
b110 '
1!
#480
0!
#500
b101 (
0%
b100 '
1!
#520
0!
#540
b1 (
1&
b101 '
1!
#560
0!
#580
b11 (
0$
b1 '
1!
#600
0!
