Encoder8to3/Encoder8to3_bh.v
module Encoder8to3_bh(EI, I, Y, GS, EO);
input EI;
input [7:0] I;
output reg [2:0] Y;
output reg GS, EO;
always @(EI, I)
begin
	if (EI == 0) begin Y = 3'b000; GS = 0; EO = 0; end
	else begin
		GS = 1;
		EO = 0;
		if (I[7]) Y = 3'b111; 
		else if (I[6]) Y = 3'b110; 
		else if (I[5]) Y = 3'b101; 
		else if (I[4]) Y = 3'b100; 
		else if (I[3]) Y = 3'b011; 
		else if (I[2]) Y = 3'b010; 
		else if (I[1]) Y = 3'b001; 
		else if (I[0]) Y = 3'b000; 
		else begin Y = 3'b000; GS = 0; EO = 1; end
	end
end
endmodule

Encoder8to3/Encoder8to3_bh_tb.vt
`timescale 1ns/100ps
`include "Encoder8to3_bh.v"

module Encoder8to3_bh_tb;
   wire GS, EO;
   reg [7:0] I;
   reg EI;
   wire [2:0] Y;
   Encoder8to3_bh En(EI, I, Y, GS, EO);
   integer k;
   initial begin
      $dumpfile("Encoder8to3_bh.vcd");
      $dumpvars(0, Encoder8to3_bh_tb);
      I = 8'b00000000;
      EI = 0;
      #1 EI = 1;
      #2 I += 1;
      for (k = 0; k < 8; k = k + 1)
         if (k == 4) begin #1 EI = 0; #1 I = I << 1; EI = 1; end
         else #2 I = I << 1;

      //for (k=0; k<8; k=k+1)
      //  #10 $display("done testing case %d", k);

      $finish;

   end

endmodule

Encoder8to3/Encoder8to3_bh.vcd
$date
	Sun Nov 22 16:53:51 2020
$end
$version
	Icarus Verilog
$end
$timescale
	100ps
$end
$scope module Encoder8to3_bh_tb $end
$var wire 3 ! Y [2:0] $end
$var wire 1 " GS $end
$var wire 1 # EO $end
$var reg 1 $ EI $end
$var reg 8 % I [7:0] $end
$var integer 32 & k [31:0] $end
$scope module En $end
$var wire 1 $ EI $end
$var wire 8 ' I [7:0] $end
$var reg 1 # EO $end
$var reg 1 " GS $end
$var reg 3 ( Y [2:0] $end
$upscope $end
$upscope $end
$enddefinitions $end
#0
$dumpvars
b0 (
b0 '
bx &
b0 %
0$
0#
0"
b0 !
$end
#10
1#
0"
1$
#30
0#
1"
b0 &
b1 %
b1 '
#50
b1 !
b1 (
b1 &
b10 %
b10 '
#70
b10 !
b10 (
b10 &
b100 %
b100 '
#90
b11 !
b11 (
b11 &
b1000 %
b1000 '
#110
b100 !
b100 (
b100 &
b10000 %
b10000 '
#120
0"
b0 !
b0 (
0$
#130
b101 !
b101 (
1"
b101 &
1$
b100000 %
b100000 '
#150
b110 !
b110 (
b110 &
b1000000 %
b1000000 '
#170
b111 !
b111 (
b111 &
b10000000 %
b10000000 '
#190
1#
0"
b0 !
b0 (
b1000 &
b0 %
b0 '
